parametric_uhpc/__init__.py
parametric_uhpc/deflection.py
parametric_uhpc/draw.py
parametric_uhpc/envelope.py
parametric_uhpc/main_model.py
parametric_uhpc/mk_equations.py
parametric_uhpc/plot_beta.py
parametric_uhpc-1.0.0.dist-info/LICENSE.txt
parametric_uhpc-1.0.0.dist-info/METADATA
parametric_uhpc-1.0.0.dist-info/WHEEL
parametric_uhpc-1.0.0.dist-info/top_level.txt
parametric_uhpc-1.0.0.dist-info/RECORD
